mcp_verification_code/__init__.py
mcp_verification_code/__main__.py
mcp_verification_code/verification_code.py
mcp_verification_code-0.1.3.dist-info/METADATA
mcp_verification_code-0.1.3.dist-info/WHEEL
mcp_verification_code-0.1.3.dist-info/entry_points.txt
mcp_verification_code-0.1.3.dist-info/top_level.txt
mcp_verification_code-0.1.3.dist-info/RECORD
