Metadata-Version: 2.4
Name: mcp-verification-code
Version: 0.1.3
Summary: 一个简单的验证码生成工具
Home-page: https://github.com/yourusername/mcp-verification-code
Author: MCP Developer
Author-email: Your Name <your.email@example.com>
Project-URL: Homepage, https://github.com/yourusername/mcp-verification-code
Project-URL: Bug Tracker, https://github.com/yourusername/mcp-verification-code/issues
Classifier: Programming Language :: Python :: 3
Classifier: License :: OSI Approved :: MIT License
Classifier: Operating System :: OS Independent
Requires-Python: >=3.13
Dynamic: author
Dynamic: home-page
